genai_labnote/__init__.py
genai_labnote/agent.py
genai_labnote/core.py
genai_labnote/llm.py
genai_labnote/magic.py
genai_labnote/storage.py
genai_labnote-0.2.0.dist-info/licenses/LICENSE
genai_labnote-0.2.0.dist-info/METADATA
genai_labnote-0.2.0.dist-info/WHEEL
genai_labnote-0.2.0.dist-info/top_level.txt
genai_labnote-0.2.0.dist-info/RECORD
